simple_greeter_cli/__init__.py
simple_greeter_cli/greeter.py
simple_greeter_cli-0.1.0.dist-info/licenses/LICENSE
simple_greeter_cli-0.1.0.dist-info/METADATA
simple_greeter_cli-0.1.0.dist-info/WHEEL
simple_greeter_cli-0.1.0.dist-info/top_level.txt
simple_greeter_cli-0.1.0.dist-info/RECORD
